examples/__init__.py
examples/basic/__init__.py
examples/basic/example_client.py
examples/basic/example_server.py
examples/connectfour/_shared.py
examples/connectfour/connectfour_client.py
examples/connectfour/connectfour_server.py
examples/tictactoe/shared.py
examples/tictactoe/tictactoe_client.py
examples/tictactoe/tictactoe_pygame_client.py
examples/tictactoe/tictactoe_server.py
hisock/__init__.py
hisock/_shared.py
hisock/client.py
hisock/constants.py
hisock/server.py
hisock/utils.py
hisock-2.0.2.dist-info/LICENSE
hisock-2.0.2.dist-info/METADATA
hisock-2.0.2.dist-info/WHEEL
hisock-2.0.2.dist-info/top_level.txt
hisock-2.0.2.dist-info/RECORD
