Metadata-Version: 2.1
Name: hisock
Version: 2.0.2
Summary: A higher-level extension of the socket module, with simpler and more efficient usages
Home-page: https://github.com/SSS-Says-Snek/hisock
Author: SSS-Says-Snek
Author-email: bmcomis2018@gmail.com
License: MIT
Classifier: License :: OSI Approved :: MIT License
Classifier: Operating System :: Microsoft :: Windows
Classifier: Operating System :: MacOS
Classifier: Operating System :: POSIX :: Linux
Classifier: Programming Language :: Python :: 3.7
Classifier: Programming Language :: Python :: 3.8
Classifier: Programming Language :: Python :: 3.9
Classifier: Programming Language :: Python :: 3.10
Requires-Python: >=3.7
License-File: LICENSE
Requires-Dist: pycryptodome (==3.17)
